datafeeds/__init__.py
datafeeds/customer_metrics/__init__.py
datafeeds/customer_metrics/weekly_metrics_data.py
datafeeds/customer_metrics/weekly_metrics_main.py
datafeeds/db/__init__.py
datafeeds/db/email_sender.py
datafeeds/db/helpers.py
datafeeds/db/redshift.py
datafeeds/db/sql_queries.py
sandbox/__init__.py
sandbox/prod_connection.py
sandbox/sandbox.py
sandbox/test_aws_wrangler.py
sandbox/test_metrics_script.py
weekly_customer_metrics-1.0.dist-info/METADATA
weekly_customer_metrics-1.0.dist-info/WHEEL
weekly_customer_metrics-1.0.dist-info/top_level.txt
weekly_customer_metrics-1.0.dist-info/RECORD
